rapidpro_flow_tools/__init__.py
rapidpro_flow_tools/flow_converter.py
rapidpro_flow_tools/parsers/__init__.py
rapidpro_flow_tools/parsers/common/__init__.py
rapidpro_flow_tools/parsers/common/cellparser.py
rapidpro_flow_tools/parsers/common/rowdatasheet.py
rapidpro_flow_tools/parsers/common/rowparser.py
rapidpro_flow_tools/parsers/common/sheetparser.py
rapidpro_flow_tools/parsers/common/tests/__init__.py
rapidpro_flow_tools/parsers/common/tests/mock_cell_parser.py
rapidpro_flow_tools/parsers/common/tests/mock_row_parser.py
rapidpro_flow_tools/parsers/common/tests/mock_sheetparser.py
rapidpro_flow_tools/parsers/common/tests/models.py
rapidpro_flow_tools/parsers/common/tests/test_cellparser.py
rapidpro_flow_tools/parsers/common/tests/test_differentways.py
rapidpro_flow_tools/parsers/common/tests/test_full_rows.py
rapidpro_flow_tools/parsers/common/tests/test_rowdatasheet.py
rapidpro_flow_tools/parsers/common/tests/test_sheetparser.py
rapidpro_flow_tools/parsers/common/tests/test_unparse.py
rapidpro_flow_tools/parsers/creation/__init__.py
rapidpro_flow_tools/parsers/creation/constants.py
rapidpro_flow_tools/parsers/creation/contentindexparser.py
rapidpro_flow_tools/parsers/creation/contentindexrowmodel.py
rapidpro_flow_tools/parsers/creation/datarowmodel.py
rapidpro_flow_tools/parsers/creation/flowparser.py
rapidpro_flow_tools/parsers/creation/flowrowmodel.py
rapidpro_flow_tools/parsers/creation/template_sheet_parser.py
rapidpro_flow_tools/parsers/creation/tests/__init__.py
rapidpro_flow_tools/parsers/creation/tests/mock_sheetreader.py
rapidpro_flow_tools/parsers/creation/tests/row_data.py
rapidpro_flow_tools/parsers/creation/tests/test_contentindexparser.py
rapidpro_flow_tools/parsers/creation/tests/test_flowparser.py
rapidpro_flow_tools/parsers/creation/tests/test_to_row_model.py
rapidpro_flow_tools/parsers/creation/tests/utils.py
rapidpro_flow_tools/parsers/creation/tests/datarowmodels/evalmodels.py
rapidpro_flow_tools-1.0.5.dist-info/LICENSE
rapidpro_flow_tools-1.0.5.dist-info/METADATA
rapidpro_flow_tools-1.0.5.dist-info/WHEEL
rapidpro_flow_tools-1.0.5.dist-info/top_level.txt
rapidpro_flow_tools-1.0.5.dist-info/RECORD
