Metadata-Version: 2.1
Name: rapidpro-flow-tools
Version: 1.0.5
Summary: Toolkit for using spreadsheets to create and modify RapidPro flows
Author-email: Ed Moss <ed.moss@eemengineering.com>
Project-URL: Homepage, https://github.com/IDEMSInternational/rapidpro-flow-toolkit
Project-URL: Bug Tracker, https://github.com/IDEMSInternational/rapidpro-flow-toolkit/issues
Classifier: Programming Language :: Python :: 3
Classifier: License :: OSI Approved :: MIT License
Classifier: Operating System :: OS Independent
Requires-Python: >=3.7
License-File: LICENSE
